metta_ul/__init__.py
metta_ul/array_like_tools.py
metta_ul/grounding_tools.py
metta_ul/numme.py
metta_ul/pdm.py
metta_ul/skl.py
metta_ul/sns.py
metta_ul/cluster/__init__.py
metta_ul/cluster/agglomerative_python.py
metta_ul/cluster/bisecting_kmeans_python.py
metta_ul/cluster/gmm_python.py
metta_ul/cluster/kmeans_python.py
metta_ul/cluster/py_dot_spectral_clustering.py
metta_ul/cluster/spectral_clustering_python.py
metta_ul-0.1.0.dist-info/licenses/LICENSE
metta_ul-0.1.0.dist-info/METADATA
metta_ul-0.1.0.dist-info/WHEEL
metta_ul-0.1.0.dist-info/top_level.txt
metta_ul-0.1.0.dist-info/RECORD
