Metadata-Version: 2.4
Name: metta-ul
Version: 0.1.0
Summary: Basic implementation of clustering algorithms in MeTTa language, including k-means, GMM, spectral clustering, and hierarchical
Author-email: Ramin Barati <rekino@gmail.com>, Amirhossein Nourani Zadeh <amirhossein.nouranizadeh@gmail.com>, Farhoud <amirhossein.nouranizadeh@gmail.com>
Project-URL: Homepage, https://github.com/SNetGrant/metta_kmeans
Requires-Python: >=3.7
License-File: LICENSE
Requires-Dist: hyperon>=0.2.2
Requires-Dist: scikit-learn
Requires-Dist: pandas
Requires-Dist: seaborn
Provides-Extra: test
Requires-Dist: pytest>=7.0; extra == "test"
Dynamic: license-file
